{
  "id": 3,
  "title": "Março",
  "subtitle": "Saia na frente na sua pré-campanha! Baixe nosso guia completo com o passo a passo para organizar sua estratégia em março de 2026 e garanta sua vitória nas eleições.",
  "published": true,
  "meta_title": "",
  "meta_description": "",
  "meta_keywords": "Marketing Digital Politico, Eleicoes 2026, Campanhas Eleitorais, Empurrao Digital, Trafego Pago, Anuncios Politicos, Redes Sociais, Gestao de Redes Sociais",
  "blog_id": 4,
  "blog_name": "EMPURRÃO DIGITAL",
  "tag_ids": [
    50,
    6,
    7,
    8,
    10,
    35,
    52,
    24
  ],
  "author": "Cristiomar Silva",
  "visits": 75,
  "url": "/blog/empurrao-digital-4/marco-3",
  "created_at": "2026-03-05 14:17:25",
  "updated_at": "2026-03-14 21:52:33",
  "word_count": 2362
}