{
  "id": 244,
  "title": "Eleições 2026: Potenciais Candidatos à Presidência e o Cenário Brasileiro",
  "subtitle": "Uma visão aprofundada sobre os nomes em ascensão, as dinâmicas políticas e os desafios que moldarão o próximo pleito presidencial no Brasil.",
  "published": true,
  "meta_title": "",
  "meta_description": "",
  "meta_keywords": "",
  "blog_id": 4,
  "blog_name": "EMPURRÃO DIGITAL",
  "tag_ids": [],
  "author": "Cristiomar Silva",
  "visits": 6,
  "url": "/blog/empurrao-digital-4/eleicoes-2026-potenciais-candidatos-a-presidencia-e-o-cenario-brasileiro-244",
  "created_at": "2026-03-16 23:14:04",
  "updated_at": "2026-03-16 23:15:42",
  "word_count": 4
}